flex_observer/__init__.py
flex_observer/admin.py
flex_observer/apps.py
flex_observer/tests.py
flex_observer/migrations/__init__.py
flex_observer/types/__init__.py
flex_observer/types/observer.py
django_flex_observer-0.0.4.dist-info/AUTHORS.rst
django_flex_observer-0.0.4.dist-info/LICENSE
django_flex_observer-0.0.4.dist-info/METADATA
django_flex_observer-0.0.4.dist-info/WHEEL
django_flex_observer-0.0.4.dist-info/top_level.txt
django_flex_observer-0.0.4.dist-info/RECORD
